GPTResearch/__init__.py
gptresearch-5.0.3.dist-info/METADATA
gptresearch-5.0.3.dist-info/WHEEL
gptresearch-5.0.3.dist-info/licenses/LICENSE.txt
gptresearch-5.0.3.dist-info/RECORD
