Metadata-Version: 2.4
Name: GPTResearch
Version: 5.0.3
Summary: An AI research bot that uses web sources
Project-URL: Homepage, https://github.com/Shayneg-eng/GPT-research
Project-URL: Issues, https://github.com/Shayneg-eng/GPT-research
Author-email: Shayne Goldstein <shayneagoldstein@gmail.com>
License-File: LICENSE.txt
Classifier: License :: OSI Approved :: GNU General Public License v3 (GPLv3)
Classifier: Operating System :: OS Independent
Classifier: Programming Language :: Python :: 3
Requires-Python: >=3.0
